Metadata-Version: 2.1
Name: smallconfig
Version: 1.0.1
Summary: A small utility for managing script specific settings and multiple configurations
Home-page: https://github.com/joedeandev/SmallConfig
Author: Joe Dean
License: unlicense
Download-URL: https://github.com/joedeandev/SmallConfig/archive/smallconfig_v1.0.1.tar.gz
Platform: UNKNOWN
